epsg_ident.py
epsg_ident/__init__.py
epsg_ident/esri_epsg.db
epsg_ident-0.1.1.dist-info/DESCRIPTION.rst
epsg_ident-0.1.1.dist-info/METADATA
epsg_ident-0.1.1.dist-info/RECORD
epsg_ident-0.1.1.dist-info/WHEEL
epsg_ident-0.1.1.dist-info/entry_points.txt
epsg_ident-0.1.1.dist-info/metadata.json
epsg_ident-0.1.1.dist-info/top_level.txt
