Metadata-Version: 2.0
Name: epsg-ident
Version: 0.1.1
Summary: Quickly get the EPSG code from a .prj file or WKT
Home-page: https://github.com/cmollet/epsg_ident
Author: Cory Mollet
Author-email: cory@corymollet.com
License: ISCL
Keywords: epsg,gis,shapefile
Platform: UNKNOWN
Classifier: Development Status :: 2 - Pre-Alpha
Classifier: Intended Audience :: Developers
Classifier: License :: OSI Approved :: ISC License (ISCL)
Classifier: Natural Language :: English
Classifier: Programming Language :: Python :: 2
Classifier: Programming Language :: Python :: 2.7
Classifier: Programming Language :: Python :: 3
Classifier: Programming Language :: Python :: 3.4
Classifier: Programming Language :: Python :: 3.5
Classifier: Topic :: Scientific/Engineering :: GIS
Classifier: Topic :: Utilities
Requires-Dist: Click
Requires-Dist: flake8
Requires-Dist: tox
Requires-Dist: twine
